{
  "keyword": {
    "mode": "keyword",
    "hits": 9,
    "total": 12,
    "rate": "9/12",
    "per_query": [
      {
        "id": "q01",
        "category": "single-book",
        "hit": false,
        "top5_books": [
          "関数型ドメインモデリング"
        ],
        "expected": [
          "データモデリングでドメインを駆動する"
        ]
      },
      {
        "id": "q02",
        "category": "single-book",
        "hit": true,
        "top5_books": [
          "技術者のためのテクニカルライティング入門講座 第2版",
          "増補改訂版 図解でわかる！理工系のためのよい文章の書き方 論文・レポートを自力で書けるようになる方法"
        ],
        "expected": [
          "技術者のためのテクニカルライティング入門講座"
        ]
      },
      {
        "id": "q03",
        "category": "single-book",
        "hit": true,
        "top5_books": [
          "データモデリングでドメインを駆動する 分散／疎結合な基幹系システムに向けて"
        ],
        "expected": [
          "データモデリングでドメインを駆動する"
        ]
      },
      {
        "id": "q04",
        "category": "single-book",
        "hit": true,
        "top5_books": [
          "技術者のためのテクニカルライティング入門講座 第2版",
          "増補改訂版 図解でわかる！理工系のためのよい文章の書き方 論文・レポートを自力で書けるようになる方法"
        ],
        "expected": [
          "技術者のためのテクニカルライティング入門講座"
        ]
      },
      {
        "id": "q05",
        "category": "single-book",
        "hit": true,
        "top5_books": [
          "GitLabに学ぶ パフォーマンスを最大化させるドキュメンテーション技術 数千ページにもわたるハンドブックを活用したテキストコミュニケーションの作法"
        ],
        "expected": [
          "GitLabに学ぶ"
        ]
      },
      {
        "id": "q06",
        "category": "single-book",
        "hit": true,
        "top5_books": [
          "関数型ドメインモデリング"
        ],
        "expected": [
          "関数型ドメインモデリング"
        ]
      },
      {
        "id": "q07",
        "category": "single-book",
        "hit": true,
        "top5_books": [
          "技術者のためのテクニカルライティング入門講座 第2版",
          "増補改訂版 図解でわかる！理工系のためのよい文章の書き方 論文・レポートを自力で書けるようになる方法"
        ],
        "expected": [
          "技術者のためのテクニカルライティング入門講座"
        ]
      },
      {
        "id": "q08",
        "category": "cross-book",
        "hit": false,
        "top5_books": [
          "関数型ドメインモデリング"
        ],
        "expected": [
          "データモデリングでドメインを駆動する",
          "関数型ドメインモデリング"
        ]
      },
      {
        "id": "q09",
        "category": "cross-book",
        "hit": true,
        "top5_books": [
          "GitLabに学ぶ パフォーマンスを最大化させるドキュメンテーション技術 数千ページにもわたるハンドブックを活用したテキストコミュニケーションの作法",
          "技術者のためのテクニカルライティング入門講座 第2版"
        ],
        "expected": [
          "技術者のためのテクニカルライティング入門講座"
        ]
      },
      {
        "id": "q10",
        "category": "cross-book",
        "hit": true,
        "top5_books": [
          "技術者のためのテクニカルライティング入門講座 第2版",
          "増補改訂版 図解でわかる！理工系のためのよい文章の書き方 論文・レポートを自力で書けるようになる方法",
          "GitLabに学ぶ パフォーマンスを最大化させるドキュメンテーション技術 数千ページにもわたるハンドブックを活用したテキストコミュニケーションの作法"
        ],
        "expected": [
          "GitLabに学ぶ"
        ]
      },
      {
        "id": "q11",
        "category": "cross-book",
        "hit": false,
        "top5_books": [
          "関数型ドメインモデリング"
        ],
        "expected": [
          "データモデリングでドメインを駆動する",
          "関数型ドメインモデリング"
        ]
      },
      {
        "id": "q12",
        "category": "conceptual",
        "hit": true,
        "top5_books": [
          "増補改訂版 図解でわかる！理工系のためのよい文章の書き方 論文・レポートを自力で書けるようになる方法",
          "技術者のためのテクニカルライティング入門講座 第2版"
        ],
        "expected": [
          "図解でわかる"
        ]
      }
    ]
  },
  "hybrid": {
    "mode": "hybrid",
    "hits": 10,
    "total": 12,
    "rate": "10/12",
    "per_query": [
      {
        "id": "q01",
        "category": "single-book",
        "hit": true,
        "top5_books": [
          "関数型ドメインモデリング",
          "データモデリングでドメインを駆動する 分散／疎結合な基幹系システムに向けて"
        ],
        "expected": [
          "データモデリングでドメインを駆動する"
        ]
      },
      {
        "id": "q02",
        "category": "single-book",
        "hit": true,
        "top5_books": [
          "増補改訂版 図解でわかる！理工系のためのよい文章の書き方 論文・レポートを自力で書けるようになる方法",
          "技術者のためのテクニカルライティング入門講座 第2版"
        ],
        "expected": [
          "技術者のためのテクニカルライティング入門講座"
        ]
      },
      {
        "id": "q03",
        "category": "single-book",
        "hit": true,
        "top5_books": [
          "データモデリングでドメインを駆動する 分散／疎結合な基幹系システムに向けて"
        ],
        "expected": [
          "データモデリングでドメインを駆動する"
        ]
      },
      {
        "id": "q04",
        "category": "single-book",
        "hit": true,
        "top5_books": [
          "技術者のためのテクニカルライティング入門講座 第2版"
        ],
        "expected": [
          "技術者のためのテクニカルライティング入門講座"
        ]
      },
      {
        "id": "q05",
        "category": "single-book",
        "hit": true,
        "top5_books": [
          "GitLabに学ぶ パフォーマンスを最大化させるドキュメンテーション技術 数千ページにもわたるハンドブックを活用したテキストコミュニケーションの作法"
        ],
        "expected": [
          "GitLabに学ぶ"
        ]
      },
      {
        "id": "q06",
        "category": "single-book",
        "hit": true,
        "top5_books": [
          "関数型ドメインモデリング"
        ],
        "expected": [
          "関数型ドメインモデリング"
        ]
      },
      {
        "id": "q07",
        "category": "single-book",
        "hit": true,
        "top5_books": [
          "増補改訂版 図解でわかる！理工系のためのよい文章の書き方 論文・レポートを自力で書けるようになる方法",
          "技術者のためのテクニカルライティング入門講座 第2版"
        ],
        "expected": [
          "技術者のためのテクニカルライティング入門講座"
        ]
      },
      {
        "id": "q08",
        "category": "cross-book",
        "hit": false,
        "top5_books": [
          "関数型ドメインモデリング"
        ],
        "expected": [
          "データモデリングでドメインを駆動する",
          "関数型ドメインモデリング"
        ]
      },
      {
        "id": "q09",
        "category": "cross-book",
        "hit": true,
        "top5_books": [
          "GitLabに学ぶ パフォーマンスを最大化させるドキュメンテーション技術 数千ページにもわたるハンドブックを活用したテキストコミュニケーションの作法",
          "技術者のためのテクニカルライティング入門講座 第2版"
        ],
        "expected": [
          "技術者のためのテクニカルライティング入門講座"
        ]
      },
      {
        "id": "q10",
        "category": "cross-book",
        "hit": true,
        "top5_books": [
          "GitLabに学ぶ パフォーマンスを最大化させるドキュメンテーション技術 数千ページにもわたるハンドブックを活用したテキストコミュニケーションの作法",
          "技術者のためのテクニカルライティング入門講座 第2版",
          "増補改訂版 図解でわかる！理工系のためのよい文章の書き方 論文・レポートを自力で書けるようになる方法"
        ],
        "expected": [
          "GitLabに学ぶ"
        ]
      },
      {
        "id": "q11",
        "category": "cross-book",
        "hit": false,
        "top5_books": [
          "関数型ドメインモデリング"
        ],
        "expected": [
          "データモデリングでドメインを駆動する",
          "関数型ドメインモデリング"
        ]
      },
      {
        "id": "q12",
        "category": "conceptual",
        "hit": true,
        "top5_books": [
          "増補改訂版 図解でわかる！理工系のためのよい文章の書き方 論文・レポートを自力で書けるようになる方法"
        ],
        "expected": [
          "図解でわかる"
        ]
      }
    ]
  },
  "ask": {
    "total": 3,
    "sources_present": 3,
    "median_total_ms": 15447.0,
    "p95_total_ms": 16435.0,
    "median_retrieval_ms": 244.0,
    "median_generation_ms": 15215.0
  }
}